speedtest.py
netspeedtest-1.0.0.dist-info/LICENSE
netspeedtest-1.0.0.dist-info/METADATA
netspeedtest-1.0.0.dist-info/WHEEL
netspeedtest-1.0.0.dist-info/entry_points.txt
netspeedtest-1.0.0.dist-info/RECORD
