Metadata-Version: 2.1
Name: netspeedtest
Version: 1.0.0
Summary: speedtest
Home-page: https://github.com/sivel/
License: Apache License, Version 2.0
Keywords: speedtest-cli,http
Author: Matt Martz
Author-email: matt@sivel.net
Requires-Python: >=3.10,<4
Classifier: License :: Other/Proprietary License
Classifier: Operating System :: MacOS
Classifier: Operating System :: Microsoft :: Windows
Classifier: Programming Language :: Python :: 3
Classifier: Programming Language :: Python :: 3.10
Classifier: Programming Language :: Python :: 3.11
Classifier: Programming Language :: Python :: 3.10
Classifier: Programming Language :: Python :: 3.11
Classifier: Topic :: Internet :: WWW/HTTP
Classifier: Topic :: Utilities
Project-URL: Repository, https://github.com/sivel/speedtest-cli
